odoo/addons/base_bank_from_iban/README.rst
odoo/addons/base_bank_from_iban/__init__.py
odoo/addons/base_bank_from_iban/__manifest__.py
odoo/addons/base_bank_from_iban/models/__init__.py
odoo/addons/base_bank_from_iban/models/account_journal.py
odoo/addons/base_bank_from_iban/models/res_bank.py
odoo/addons/base_bank_from_iban/models/res_partner_bank.py
odoo/addons/base_bank_from_iban/static/description/icon.png
odoo/addons/base_bank_from_iban/tests/__init__.py
odoo/addons/base_bank_from_iban/tests/test_base_bank_from_iban.py
odoo/addons/base_bank_from_iban/views/res_bank_view.xml
odoo11_addon_base_bank_from_iban-11.0.1.0.0.dist-info/DESCRIPTION.rst
odoo11_addon_base_bank_from_iban-11.0.1.0.0.dist-info/METADATA
odoo11_addon_base_bank_from_iban-11.0.1.0.0.dist-info/RECORD
odoo11_addon_base_bank_from_iban-11.0.1.0.0.dist-info/WHEEL
odoo11_addon_base_bank_from_iban-11.0.1.0.0.dist-info/metadata.json
odoo11_addon_base_bank_from_iban-11.0.1.0.0.dist-info/top_level.txt
